{
  "login__valid_login": {
    "module": "login",
    "scenario": "valid_login",
    "steps": [
      {
        "action": "navigate",
        "value": "http://localhost:4000/testapp"
      },
      {
        "action": "type",
        "selector": "#username",
        "value": "admin"
      },
      {
        "action": "type",
        "selector": "#password",
        "value": "admin"
      },
      {
        "action": "click",
        "selector": "#submit-btn"
      },
      {
        "action": "expectUrl",
        "value": "http://localhost:4000/dashboard"
      }
    ],
    "savedAt": "2026-04-19T15:16:52.788Z"
  },
  "login__invalid_password": {
    "module": "login",
    "scenario": "invalid_password",
    "steps": [
      {
        "action": "navigate",
        "value": "http://localhost:4000/testapp"
      },
      {
        "action": "type",
        "selector": "#username",
        "value": "admin"
      },
      {
        "action": "type",
        "selector": "#password",
        "value": "wrongpassword"
      },
      {
        "action": "click",
        "selector": "#submit-btn"
      },
      {
        "action": "expect",
        "selector": "#error"
      }
    ],
    "savedAt": "2026-04-19T15:16:55.547Z"
  },
  "login__empty_fields": {
    "module": "login",
    "scenario": "empty_fields",
    "steps": [
      {
        "action": "navigate",
        "value": "http://localhost:4000/testapp"
      },
      {
        "action": "click",
        "selector": "#submit-btn"
      },
      {
        "action": "expect",
        "selector": "#error"
      }
    ],
    "savedAt": "2026-04-19T15:16:58.253Z"
  },
  "dashboard__dashboard_loads": {
    "id": "dashboard_loads",
    "module": "dashboard",
    "scenario": "dashboard_loads",
    "steps": [
      {
        "action": "navigate",
        "value": "http://localhost:4000/testapp"
      },
      {
        "action": "type",
        "selector": "#username",
        "value": "admin"
      },
      {
        "action": "type",
        "selector": "#password",
        "value": "admin"
      },
      {
        "action": "click",
        "selector": "#submit-btn"
      },
      {
        "action": "waitForNavigation"
      },
      {
        "action": "expectUrl",
        "value": "http://localhost:4000/dashboard"
      },
      {
        "action": "expect",
        "selector": "#page-title"
      },
      {
        "action": "assertText",
        "selector": "#page-title",
        "value": "Dashboard"
      },
      {
        "action": "expect",
        "selector": "#welcome-msg"
      }
    ],
    "savedAt": "2026-04-19T15:16:45.784Z"
  },
  "dashboard__navigate_to_projects": {
    "module": "dashboard",
    "scenario": "navigate_to_projects",
    "steps": [
      {
        "action": "navigate",
        "value": "http://localhost:4000/testapp"
      },
      {
        "action": "type",
        "selector": "#username",
        "value": "admin"
      },
      {
        "action": "type",
        "selector": "#password",
        "value": "admin"
      },
      {
        "action": "click",
        "selector": "#submit-btn"
      },
      {
        "action": "waitForNavigation"
      },
      {
        "action": "click",
        "selector": "#view-projects-btn"
      },
      {
        "action": "waitForNavigation"
      },
      {
        "action": "expectUrl",
        "value": "http://localhost:4000/project"
      }
    ],
    "savedAt": "2026-04-19T15:16:49.972Z"
  },
  "navigation__full_login_flow": {
    "id": "full_login_flow",
    "module": "navigation",
    "scenario": "full_login_flow",
    "steps": [
      {
        "action": "navigate",
        "value": "http://localhost:4000/testapp"
      },
      {
        "action": "type",
        "selector": "#username",
        "value": "admin"
      },
      {
        "action": "type",
        "selector": "#password",
        "value": "admin"
      },
      {
        "action": "click",
        "selector": "#submit-btn"
      },
      {
        "action": "waitForNavigation"
      },
      {
        "action": "expectUrl",
        "value": "http://localhost:4000/dashboard"
      },
      {
        "action": "assertText",
        "selector": "#page-title",
        "value": "Dashboard"
      },
      {
        "action": "click",
        "selector": "#nav-projects"
      },
      {
        "action": "waitForNavigation"
      },
      {
        "action": "expectUrl",
        "value": "http://localhost:4000/projects"
      },
      {
        "action": "assertText",
        "selector": "#projects-heading",
        "value": "Projects"
      }
    ],
    "savedAt": "2026-04-19T15:17:02.256Z"
  },
  "navigation__logout_flow": {
    "id": "logout_flow",
    "module": "navigation",
    "scenario": "logout_flow",
    "steps": [
      {
        "action": "navigate",
        "value": "http://localhost:4000/testapp"
      },
      {
        "action": "type",
        "selector": "#username",
        "value": "admin"
      },
      {
        "action": "type",
        "selector": "#password",
        "value": "admin"
      },
      {
        "action": "click",
        "selector": "#submit-btn"
      },
      {
        "action": "waitForNavigation"
      },
      {
        "action": "expectUrl",
        "value": "http://localhost:4000/dashboard"
      },
      {
        "action": "click",
        "selector": "#logout-link"
      },
      {
        "action": "waitForNavigation"
      },
      {
        "action": "expectUrl",
        "value": "http://localhost:4000/testapp"
      },
      {
        "action": "expect",
        "selector": "#username"
      }
    ],
    "savedAt": "2026-04-19T15:17:06.189Z"
  },
  "profile__view_profile": {
    "id": "view_profile",
    "module": "profile",
    "scenario": "view_profile",
    "steps": [
      {
        "action": "navigate",
        "value": "http://localhost:4000/testapp"
      },
      {
        "action": "type",
        "selector": "#username",
        "value": "admin"
      },
      {
        "action": "type",
        "selector": "#password",
        "value": "admin"
      },
      {
        "action": "click",
        "selector": "#submit-btn"
      },
      {
        "action": "waitForNavigation"
      },
      {
        "action": "navigate",
        "value": "http://localhost:4000/profile"
      },
      {
        "action": "expect",
        "selector": "#profile-heading"
      },
      {
        "action": "expect",
        "selector": "#profile-name"
      }
    ],
    "savedAt": "2026-04-19T15:17:10.038Z"
  },
  "profile__save_profile": {
    "id": "save_profile",
    "module": "profile",
    "scenario": "save_profile",
    "steps": [
      {
        "action": "navigate",
        "value": "http://localhost:4000/testapp"
      },
      {
        "action": "type",
        "selector": "#username",
        "value": "admin"
      },
      {
        "action": "type",
        "selector": "#password",
        "value": "admin"
      },
      {
        "action": "click",
        "selector": "#submit-btn"
      },
      {
        "action": "waitForNavigation"
      },
      {
        "action": "navigate",
        "value": "http://localhost:4000/profile"
      },
      {
        "action": "type",
        "selector": "#profile-email",
        "value": "new.admin@example.com"
      },
      {
        "action": "click",
        "selector": "#save-profile-btn"
      },
      {
        "action": "expect",
        "selector": "#save-msg"
      }
    ],
    "savedAt": "2026-04-19T15:17:13.958Z"
  },
  "projects__create_project": {
    "id": "create_project",
    "module": "projects",
    "scenario": "create_project",
    "steps": [
      {
        "action": "navigate",
        "value": "http://localhost:4000/testapp"
      },
      {
        "action": "type",
        "selector": "#username",
        "value": "admin"
      },
      {
        "action": "type",
        "selector": "#password",
        "value": "admin"
      },
      {
        "action": "click",
        "selector": "#submit-btn"
      },
      {
        "action": "waitForNavigation"
      },
      {
        "action": "navigate",
        "value": "http://localhost:4000/projects"
      },
      {
        "action": "click",
        "selector": "#new-project-btn"
      },
      {
        "action": "type",
        "selector": "#project-name-input",
        "value": "Delta"
      },
      {
        "action": "click",
        "selector": "#create-project-btn"
      },
      {
        "action": "expect",
        "selector": "#success-msg"
      }
    ],
    "savedAt": "2026-04-19T15:17:17.921Z"
  },
  "projects__cancel_modal": {
    "id": "cancel_modal",
    "module": "projects",
    "scenario": "cancel_modal",
    "steps": [
      {
        "action": "navigate",
        "value": "http://localhost:4000/testapp"
      },
      {
        "action": "type",
        "selector": "#username",
        "value": "admin"
      },
      {
        "action": "type",
        "selector": "#password",
        "value": "admin"
      },
      {
        "action": "click",
        "selector": "#submit-btn"
      },
      {
        "action": "waitForNavigation"
      },
      {
        "action": "navigate",
        "value": "http://localhost:4000/projects"
      },
      {
        "action": "click",
        "selector": "#new-project-btn"
      },
      {
        "action": "click",
        "selector": "#cancel-btn"
      },
      {
        "action": "expect",
        "selector": "#new-project-btn"
      }
    ],
    "savedAt": "2026-04-19T15:17:21.894Z"
  }
}